mango_auth/__init__.py
mango_auth/__main__.py
mango_auth/pam_interactive.py
mango_auth-0.0.7.dist-info/licenses/LICENSE
mango_auth-0.0.7.dist-info/METADATA
mango_auth-0.0.7.dist-info/WHEEL
mango_auth-0.0.7.dist-info/entry_points.txt
mango_auth-0.0.7.dist-info/top_level.txt
mango_auth-0.0.7.dist-info/RECORD
