Metadata-Version: 2.4
Name: mango_auth
Version: 0.0.7
Summary: Mango Auth is a small python module to authenticate using interactive pam authentication against an iRODS installation, opening web browser links as needed.
Author-email: Peter Verraedt <peter.verraedt@kuleuven.be>
License-Expression: BSD-3-Clause
Project-URL: repository, https://github.com/kuleuven/mango-auth
Requires-Python: >=3.8
License-File: LICENSE
Requires-Dist: python-irodsclient>=3.2.0
Dynamic: license-file
